pypoolparty/__init__.py
pypoolparty/chunking.py
pypoolparty/debugging.py
pypoolparty/job_counter.py
pypoolparty/making_script.py
pypoolparty/pooling.py
pypoolparty/proto_pool.py
pypoolparty/testing.py
pypoolparty/utils.py
pypoolparty/version.py
pypoolparty/slurm/__init__.py
pypoolparty/slurm/calling.py
pypoolparty/slurm/organizing_jobs.py
pypoolparty/slurm/testing.py
pypoolparty/slurm/array/__init__.py
pypoolparty/slurm/array/debugging.py
pypoolparty/slurm/array/making_script.py
pypoolparty/slurm/array/mapping.py
pypoolparty/slurm/array/polling.py
pypoolparty/slurm/array/reducing.py
pypoolparty/slurm/array/utils.py
pypoolparty/slurm/tests/resources/dummy_queue_state.json
pypoolparty/slurm/tests/resources/dummy_sbatch.py
pypoolparty/slurm/tests/resources/dummy_scancel.py
pypoolparty/slurm/tests/resources/dummy_squeue.py
pypoolparty/slurm/tests/resources/squeue_format_all.stdout
pypoolparty/sun_grid_engine/__init__.py
pypoolparty/sun_grid_engine/calling.py
pypoolparty/sun_grid_engine/organizing_jobs.py
pypoolparty/sun_grid_engine/testing.py
pypoolparty/sun_grid_engine/tests/resources/dummy_qdel.py
pypoolparty/sun_grid_engine/tests/resources/dummy_qstat.py
pypoolparty/sun_grid_engine/tests/resources/dummy_qsub.py
pypoolparty-0.3.1.dist-info/LICENSE
pypoolparty-0.3.1.dist-info/METADATA
pypoolparty-0.3.1.dist-info/WHEEL
pypoolparty-0.3.1.dist-info/top_level.txt
pypoolparty-0.3.1.dist-info/RECORD
