Metadata-Version: 2.1
Name: pypoolparty
Version: 0.3.1
Summary: A job pool for distributed compute clusters inspired by python's multoprocessing.Pool.
Home-page: https://github.com/cherenkov-plenoscope/pypoolparty
Author: Sebastian Achim Mueller
Author-email: sebastian-achim.mueller@mpi-hd.mpg.de
Classifier: Programming Language :: Python :: 3
Classifier: License :: OSI Approved :: MIT License
Classifier: Operating System :: OS Independent
Classifier: Natural Language :: English
License-File: LICENSE
Requires-Dist: qstat >=0.0.5
Requires-Dist: json-lines >=0.5.0
Requires-Dist: json-line-logger >=0.0.9
Requires-Dist: rename-after-writing >=0.0.5
